metaspread/__init__.py
metaspread/__main__.py
metaspread/cancercell.py
metaspread/cancermodel.py
metaspread/configs.py
metaspread/datagenerator.py
metaspread/graphgenerator.py
metaspread/interactive.py
metaspread/quasicircle.py
metaspread/simrunner.py
metaspread/vessel.py
metaspread/videogenerator.py
metaspread-2024.0.5.dist-info/METADATA
metaspread-2024.0.5.dist-info/WHEEL
metaspread-2024.0.5.dist-info/licenses/LICENSE.txt
metaspread-2024.0.5.dist-info/RECORD
